HexSpinbox/HexSpinbox.py
HexSpinbox/__init__.py
hexspinbox-0.1.0.dist-info/licenses/LICENSE
hexspinbox-0.1.0.dist-info/METADATA
hexspinbox-0.1.0.dist-info/WHEEL
hexspinbox-0.1.0.dist-info/top_level.txt
hexspinbox-0.1.0.dist-info/RECORD
