Metadata-Version: 2.4
Name: HexSpinbox
Version: 0.1.0
Summary: A simple Python Tkinter widget for displaying hexadecimal integers in a (ttk) spin box.
Author-email: sayofan <sayofan+HexSpinbox@proton.me>
License-Expression: MIT
Project-URL: Homepage, https://github.com/sayofan/HexSpinbox
Keywords: tkinter,GUI
Classifier: Programming Language :: Python :: 3
Classifier: Operating System :: OS Independent
Classifier: Intended Audience :: Developers
Classifier: Topic :: Desktop Environment
Classifier: Topic :: Software Development
Classifier: Topic :: Software Development :: Libraries :: Python Modules
Classifier: Topic :: Software Development :: Libraries :: Tcl Extensions
Requires-Python: >=3.7
License-File: LICENSE
Dynamic: license-file
